codec/__init__.py
codec/auth.py
codec/client.py
codec/constants.py
codec/exceptions.py
codec/resources/__init__.py
codec/resources/logger.py
codec/resources/request.py
codec/resources/collections/__init__.py
codec/resources/collections/collections.py
codec/resources/collections/format.py
codec/resources/collections/types.py
codec/resources/search/__init__.py
codec/resources/search/search.py
codec/resources/search/types.py
codec/resources/videos/__init__.py
codec/resources/videos/format.py
codec/resources/videos/types.py
codec/resources/videos/videos.py
codec/resources/webhook/__init__.py
codec/resources/webhook/webhook.py
codec/utils/__init__.py
codec/utils/file_utils.py
codec/utils/type_utils.py
codec_sdk-0.2.9.dist-info/LICENSE
codec_sdk-0.2.9.dist-info/WHEEL
codec_sdk-0.2.9.dist-info/METADATA
codec_sdk-0.2.9.dist-info/RECORD
